MANIFEST.in
README.md
requirements.txt
setup.py
mlphys_nightly.egg-info/SOURCES.txt
mlphys_nightly.egg-info/dependency_links.txt
mlphys_nightly.egg-info/top_level.txt
mlphys_nightly_super/__init__.py
mlphys_nightly_super.egg-info/PKG-INFO
mlphys_nightly_super.egg-info/SOURCES.txt
mlphys_nightly_super.egg-info/dependency_links.txt
mlphys_nightly_super.egg-info/top_level.txt
mlphys_nightly_super/deepqis/__init__.py
mlphys_nightly_super/deepqis/Simulator/Distributions.py
mlphys_nightly_super/deepqis/Simulator/Measurements.py
mlphys_nightly_super/deepqis/Simulator/__init__.py
mlphys_nightly_super/deepqis/network/Inference.py
mlphys_nightly_super/deepqis/network/__init__.py
mlphys_nightly_super/deepqis/network/models/ARL_ONRL_meas_n_1000_qubits_2_batch_4_alpha_0.1_BEST.h5
mlphys_nightly_super/deepqis/network/models/ARL_ONRL_meas_n_1000_qubits_2_batch_4_alpha_0.4_BEST.h5
mlphys_nightly_super/deepqis/utils/Alpha_Measure.py
mlphys_nightly_super/deepqis/utils/Concurrence_Measure.py
mlphys_nightly_super/deepqis/utils/Extract_Net.py
mlphys_nightly_super/deepqis/utils/Fidelity_Measure.py
mlphys_nightly_super/deepqis/utils/Max_Eigen_Measure.py
mlphys_nightly_super/deepqis/utils/Purity_Measure.py
mlphys_nightly_super/deepqis/utils/Rank_Measure.py
mlphys_nightly_super/deepqis/utils/__init__.py
mlphys_nightly_super/deepqis/utils/gen_basis_array.py
mlphys_nightly_super/deepqis/utils/gen_basis_order.py
mlphys_nightly_super/deepqis/utils/projectors_array_qs_2.pickle